tafel-2025.5.6.dist-info/METADATA
tafel-2025.5.6.dist-info/WHEEL
tafel-2025.5.6.dist-info/entry_points.txt
tafel/__init__.py
tafel/app/__init__.py
tafel/app/cli.py
tafel/core/__init__.py
tafel/core/bo.py
tafel/core/reader.py
tafel-2025.5.6.dist-info/RECORD
