Metadata-Version: 2.1
Name: tafel
Version: 2025.5.6
Summary: A python package to extract Tafel slope
Author-Email: Koki Muraoka <muraok_k@chemsys.t.u-tokyo.ac.jp>
License: MIT
Requires-Python: >=3.11
Requires-Dist: optuna==4.2.1
Requires-Dist: pandas==2.2.3
Requires-Dist: plotly==6.0.0
Requires-Dist: scipy==1.15.1
Requires-Dist: scikit-learn==1.6.1
Requires-Dist: kaleido==0.2.1
